roofline/__init__.py
roofline/roofline.py
roofline_plotter-0.1.1.post0.dist-info/licenses/LICENSE
roofline_plotter-0.1.1.post0.dist-info/METADATA
roofline_plotter-0.1.1.post0.dist-info/WHEEL
roofline_plotter-0.1.1.post0.dist-info/top_level.txt
roofline_plotter-0.1.1.post0.dist-info/RECORD
