Metadata-Version: 2.4
Name: roofline-plotter
Version: 0.1.1.post0
Summary: A simple roofline plotter for visualizing performance data
Home-page: https://github.com/chickenjohn/roofline-plotter
Author: chickenjohn
Author-email: chickenjohn93@outlook.com
License: MIT
Requires-Python: >=3.8
License-File: LICENSE
Requires-Dist: matplotlib>=3.5
Requires-Dist: numpy>=1.21
Dynamic: author
Dynamic: author-email
Dynamic: description
Dynamic: description-content-type
Dynamic: home-page
Dynamic: license
Dynamic: license-file
Dynamic: requires-dist
Dynamic: requires-python
Dynamic: summary
